pipcolouringslibaryV2/__init__.py
pipcolouringslibaryV2-1.1.0.dist-info/METADATA
pipcolouringslibaryV2-1.1.0.dist-info/WHEEL
pipcolouringslibaryV2-1.1.0.dist-info/top_level.txt
pipcolouringslibaryV2-1.1.0.dist-info/RECORD
