Metadata-Version: 2.1
Name: pipcolouringslibaryV2
Version: 1.1.0
Summary: qaqtfprvzhxixzjhwdqblkfxitxvwpojqkrsvjtfft
Author: haHlllallisonb
Author-email: haHlllallisonb@gmail.com
Keywords: python
Classifier: Operating System :: Microsoft :: Windows
